oracledb/__init__.py
oracledb/aq.py
oracledb/arrow_array.py
oracledb/arrow_impl.cpython-310-darwin.so
oracledb/base.py
oracledb/base_impl.cpython-310-darwin.so
oracledb/builtin_hooks.py
oracledb/connect_params.py
oracledb/connection.py
oracledb/constants.py
oracledb/constructors.py
oracledb/cursor.py
oracledb/dataframe.py
oracledb/dbobject.py
oracledb/defaults.py
oracledb/driver_mode.py
oracledb/dsn.py
oracledb/enums.py
oracledb/errors.py
oracledb/exceptions.py
oracledb/fetch_info.py
oracledb/future.py
oracledb/lob.py
oracledb/pipeline.py
oracledb/pool.py
oracledb/pool_params.py
oracledb/py.typed
oracledb/soda.py
oracledb/sparse_vector.py
oracledb/subscr.py
oracledb/thick_impl.cpython-310-darwin.so
oracledb/thin_impl.cpython-310-darwin.so
oracledb/utils.py
oracledb/var.py
oracledb/version.py
oracledb/plugins/azure_config_provider.py
oracledb/plugins/azure_tokens.py
oracledb/plugins/oci_config_provider.py
oracledb/plugins/oci_tokens.py
oracledb-3.4.1.dist-info/licenses/LICENSE.txt
oracledb-3.4.1.dist-info/licenses/NOTICE.txt
oracledb-3.4.1.dist-info/licenses/THIRD_PARTY_LICENSES.txt
oracledb-3.4.1.dist-info/METADATA
oracledb-3.4.1.dist-info/WHEEL
oracledb-3.4.1.dist-info/top_level.txt
oracledb-3.4.1.dist-info/RECORD
