Metadata-Version: 2.4
Name: oracledb
Version: 3.4.1
Summary: Python interface to Oracle Database
Author-email: Anthony Tuininga <anthony.tuininga@oracle.com>
License-Expression: UPL-1.0 OR Apache-2.0
Project-URL: Homepage, https://oracle.github.io/python-oracledb
Project-URL: Installation, https://python-oracledb.readthedocs.io/en/latest/user_guide/installation.html
Project-URL: Samples, https://github.com/oracle/python-oracledb/tree/main/samples
Project-URL: Documentation, http://python-oracledb.readthedocs.io
Project-URL: Release Notes, https://python-oracledb.readthedocs.io/en/latest/release_notes.html
Project-URL: Issues, https://github.com/oracle/python-oracledb/issues
Project-URL: Source, https://github.com/oracle/python-oracledb
Keywords: Oracle,database
Classifier: Development Status :: 5 - Production/Stable
Classifier: Intended Audience :: Developers
Classifier: Natural Language :: English
Classifier: Operating System :: OS Independent
Classifier: Programming Language :: Python :: 3 :: Only
Classifier: Programming Language :: Python :: 3.9
Classifier: Programming Language :: Python :: 3.10
Classifier: Programming Language :: Python :: 3.11
Classifier: Programming Language :: Python :: 3.12
Classifier: Programming Language :: Python :: 3.13
Classifier: Programming Language :: Python :: 3.14
Classifier: Programming Language :: Python :: Implementation :: CPython
Classifier: Programming Language :: Cython
Classifier: Topic :: Database
Requires-Python: >=3.9
License-File: LICENSE.txt
License-File: THIRD_PARTY_LICENSES.txt
License-File: NOTICE.txt
Requires-Dist: cryptography>=3.2.1
Requires-Dist: typing_extensions>=4.14.0
Provides-Extra: test
Requires-Dist: anyio; extra == "test"
Requires-Dist: numpy; extra == "test"
Requires-Dist: pandas; extra == "test"
Requires-Dist: pyarrow; extra == "test"
Requires-Dist: pytest; extra == "test"
Provides-Extra: oci-config
Requires-Dist: oci; extra == "oci-config"
Provides-Extra: oci-auth
Requires-Dist: oci; extra == "oci-auth"
Provides-Extra: azure-config
Requires-Dist: azure-appconfiguration; extra == "azure-config"
Requires-Dist: azure-identity; extra == "azure-config"
Requires-Dist: azure-keyvault-secrets; extra == "azure-config"
Provides-Extra: azure-auth
Requires-Dist: msal; extra == "azure-auth"
Dynamic: license-file
